goes_dl-0.3rc1.dist-info/licenses/LICENSE
goesdl/__init__.py
goesdl/info.py
goesdl/py.typed
goesdl/dataset/__init__.py
goesdl/dataset/locator.py
goesdl/dataset/locator_gg.py
goesdl/datasource/__init__.py
goesdl/datasource/datasource.py
goesdl/datasource/datasource_aws.py
goesdl/datasource/datasource_base.py
goesdl/datasource/datasource_cache.py
goesdl/datasource/datasource_http.py
goesdl/datasource/datasource_local.py
goesdl/datasource/datasource_ncei.py
goesdl/downloader/__init__.py
goesdl/downloader/constants.py
goesdl/downloader/downloader.py
goesdl/downloader/downloader_base.py
goesdl/enhancement/__init__.py
goesdl/enhancement/catalogue.py
goesdl/enhancement/clr_table.py
goesdl/enhancement/colormap.py
goesdl/enhancement/constants.py
goesdl/enhancement/cpt_table.py
goesdl/enhancement/eu_table.py
goesdl/enhancement/palette.py
goesdl/enhancement/preview.py
goesdl/enhancement/scale.py
goesdl/enhancement/shared.py
goesdl/enhancement/stretching.py
goesdl/enhancement/table.py
goesdl/enhancement/ticks.py
goesdl/enhancement/utility.py
goesdl/experimental/__init__.py
goesdl/experimental/animation.py
goesdl/experimental/conventions.py
goesdl/experimental/fileio.py
goesdl/experimental/fourier.py
goesdl/experimental/geodesy.py
goesdl/experimental/netcdf.py
goesdl/experimental/plotting.py
goesdl/experimental/profile.py
goesdl/experimental/reproject.py
goesdl/experimental/topology.py
goesdl/geodesy/__init__.py
goesdl/geodesy/aeqdproj_parameters.py
goesdl/geodesy/azimuthal_equidistant_parameters.py
goesdl/geodesy/geos_to_latlon_grid.py
goesdl/geodesy/geos_to_latlon_grid_cartopy.py
goesdl/geodesy/geos_to_latlon_grid_goesdl.py
goesdl/geodesy/geos_to_latlon_grid_pyproj.py
goesdl/geodesy/geostationary_parameters.py
goesdl/geodesy/helpers.py
goesdl/geodesy/rectangular_region.py
goesdl/goesr/__init__.py
goesdl/goesr/constants.py
goesdl/goesr/databook_gr.py
goesdl/goesr/dataset_info.py
goesdl/goesr/dataset_time.py
goesdl/goesr/geodetic.py
goesdl/goesr/image.py
goesdl/goesr/locator.py
goesdl/goesr/locator_abi.py
goes_dl-0.3rc1.dist-info/METADATA
goes_dl-0.3rc1.dist-info/WHEEL
goes_dl-0.3rc1.dist-info/top_level.txt
goes_dl-0.3rc1.dist-info/RECORD
