Metadata-Version: 2.4
Name: goes-dl
Version: 0.3rc1
Summary: GOES-DL — GOES Satellite Imagery Dataset Accessing Toolbox
Author-email: Waldemar Villamayor-Venialbo <wvenialbo@fpuna.edu.py>
License-Expression: MIT
Project-URL: Issues, https://github.com/wvenialbo/GOES-DL/issues
Project-URL: Repository, https://github.com/wvenialbo/GOES-DL
Keywords: climate,meteorology,oceanography,atmospheric science,planetary science,geodesy,science,satellite imagery,environmental data,severe weather,GOES,GOES-R,GridSat,GridSat-B1,GridSat-CONUS,GridSat-GOES,GridSat-GOES/CONUS,netcdf,data,dataset,downloader,multi-source
Classifier: Development Status :: 3 - Alpha
Classifier: Intended Audience :: Developers
Classifier: Intended Audience :: Education
Classifier: Intended Audience :: Science/Research
Classifier: Natural Language :: English
Classifier: Operating System :: OS Independent
Classifier: Programming Language :: Python :: 3
Classifier: Programming Language :: Python :: 3.10
Classifier: Programming Language :: Python :: 3.11
Classifier: Programming Language :: Python :: 3.12
Classifier: Programming Language :: Python :: 3.13
Classifier: Topic :: Education
Classifier: Topic :: Internet :: WWW/HTTP :: Indexing/Search
Classifier: Topic :: Scientific/Engineering :: Atmospheric Science
Classifier: Topic :: Scientific/Engineering :: GIS
Classifier: Topic :: Scientific/Engineering :: Information Analysis
Classifier: Topic :: Software Development :: Libraries :: Python Modules
Classifier: Topic :: Utilities
Requires-Python: >=3.10
License-File: LICENSE
Requires-Dist: boto3
Requires-Dist: cartopy
Requires-Dist: matplotlib
Requires-Dist: netCDF4
Requires-Dist: numpy
Requires-Dist: pillow
Requires-Dist: pyproj
Requires-Dist: requests
Dynamic: license-file
